[
  {
    "line": 1,
    "elements": [
      {
        "before": [
          {
            "result": {
              "duration": 1059000,
              "status": "passed"
            },
            "match": {
              "location": "StepDefinination.beforeHooks(Scenario)"
            }
          }
        ],
        "line": 12,
        "name": "Login functionality",
        "description": "",
        "id": "checking-the-booking-functionality-of-adacitin-app;login-functionality;;2",
        "after": [
          {
            "result": {
              "duration": 632236700,
              "status": "passed"
            },
            "match": {
              "location": "StepDefinination.afterHooks(Scenario)"
            }
          }
        ],
        "type": "scenario",
        "keyword": "Scenario Outline",
        "steps": [
          {
            "result": {
              "duration": 2939197300,
              "error_message": "org.openqa.selenium.WebDriverException: unknown error: net::ERR_INTERNET_DISCONNECTED\n  (Session info: chrome\u003d103.0.5060.66)\nBuild info: version: \u00273.141.59\u0027, revision: \u0027e82be7d358\u0027, time: \u00272018-11-14T08:17:03\u0027\nSystem info: host: \u0027DESKTOP-2V7MRDA\u0027, ip: \u0027127.0.0.1\u0027, os.name: \u0027Windows 10\u0027, os.arch: \u0027amd64\u0027, os.version: \u002710.0\u0027, java.version: \u00271.8.0_281\u0027\nDriver info: org.openqa.selenium.chrome.ChromeDriver\nCapabilities {acceptInsecureCerts: false, browserName: chrome, browserVersion: 103.0.5060.66, chrome: {chromedriverVersion: 103.0.5060.53 (a1711811edd7..., userDataDir: C:\\Users\\Luman\\AppData\\Loca...}, goog:chromeOptions: {debuggerAddress: localhost:52653}, javascriptEnabled: true, networkConnectionEnabled: false, pageLoadStrategy: normal, platform: WINDOWS, platformName: WINDOWS, proxy: Proxy(), setWindowRect: true, strictFileInteractability: false, timeouts: {implicit: 0, pageLoad: 300000, script: 30000}, unhandledPromptBehavior: dismiss and notify, webauthn:extension:credBlob: true, webauthn:extension:largeBlob: true, webauthn:virtualAuthenticators: true}\nSession ID: 56e9a8e4f1a461a1426671a1c28a0d45\r\n\tat sun.reflect.NativeConstructorAccessorImpl.newInstance0(Native Method)\r\n\tat sun.reflect.NativeConstructorAccessorImpl.newInstance(Unknown Source)\r\n\tat sun.reflect.DelegatingConstructorAccessorImpl.newInstance(Unknown Source)\r\n\tat java.lang.reflect.Constructor.newInstance(Unknown Source)\r\n\tat org.openqa.selenium.remote.http.W3CHttpResponseCodec.createException(W3CHttpResponseCodec.java:187)\r\n\tat org.openqa.selenium.remote.http.W3CHttpResponseCodec.decode(W3CHttpResponseCodec.java:122)\r\n\tat org.openqa.selenium.remote.http.W3CHttpResponseCodec.decode(W3CHttpResponseCodec.java:49)\r\n\tat org.openqa.selenium.remote.HttpCommandExecutor.execute(HttpCommandExecutor.java:158)\r\n\tat org.openqa.selenium.remote.service.DriverCommandExecutor.execute(DriverCommandExecutor.java:83)\r\n\tat org.openqa.selenium.remote.RemoteWebDriver.execute(RemoteWebDriver.java:552)\r\n\tat org.openqa.selenium.remote.RemoteWebDriver.get(RemoteWebDriver.java:277)\r\n\tat com.Adcitin_And_Cucumber.BaseClass.getUrl(BaseClass.java:60)\r\n\tat com.stepdefination.StepDefinination.user_Must_Launch_The_Url_Of_Adacitin(StepDefinination.java:43)\r\n\tat ✽.Given user Must Launch The Url Of Adacitin(Adacitin.feature:5)\r\n",
              "status": "failed"
            },
            "line": 5,
            "name": "user Must Launch The Url Of Adacitin",
            "match": {
              "location": "StepDefinination.user_Must_Launch_The_Url_Of_Adacitin()"
            },
            "keyword": "Given "
          },
          {
            "result": {
              "status": "skipped"
            },
            "line": 6,
            "name": "user Entering The \"Darthvader\" In The Username Field",
            "match": {
              "arguments": [
                {
                  "val": "Darthvader",
                  "offset": 19
                }
              ],
              "location": "StepDefinination.user_Entering_The_In_The_Username_Field(String)"
            },
            "matchedColumns": [
              0
            ],
            "keyword": "When "
          },
          {
            "result": {
              "status": "skipped"
            },
            "line": 7,
            "name": "user Entering The \"darklord123\" In The Password Field",
            "match": {
              "arguments": [
                {
                  "val": "darklord123",
                  "offset": 19
                }
              ],
              "location": "StepDefinination.user_Entering_The_In_The_Password_Field(String)"
            },
            "matchedColumns": [
              1
            ],
            "keyword": "And "
          },
          {
            "result": {
              "status": "skipped"
            },
            "line": 8,
            "name": "user Click The Login Button And It Navigates To The Search Hotel Page",
            "match": {
              "location": "StepDefinination.user_Click_The_Login_Button_And_It_Navigates_To_The_Search_Hotel_Page()"
            },
            "keyword": "Then "
          }
        ],
        "tags": [
          {
            "line": 3,
            "name": "@Login"
          }
        ]
      },
      {
        "before": [
          {
            "result": {
              "duration": 963500,
              "status": "passed"
            },
            "match": {
              "location": "StepDefinination.beforeHooks(Scenario)"
            }
          }
        ],
        "line": 13,
        "name": "Login functionality",
        "description": "",
        "id": "checking-the-booking-functionality-of-adacitin-app;login-functionality;;3",
        "after": [
          {
            "result": {
              "duration": 304423100,
              "status": "passed"
            },
            "match": {
              "location": "StepDefinination.afterHooks(Scenario)"
            }
          }
        ],
        "type": "scenario",
        "keyword": "Scenario Outline",
        "steps": [
          {
            "result": {
              "duration": 403359200,
              "error_message": "org.openqa.selenium.WebDriverException: unknown error: net::ERR_INTERNET_DISCONNECTED\n  (Session info: chrome\u003d103.0.5060.66)\nBuild info: version: \u00273.141.59\u0027, revision: \u0027e82be7d358\u0027, time: \u00272018-11-14T08:17:03\u0027\nSystem info: host: \u0027DESKTOP-2V7MRDA\u0027, ip: \u0027127.0.0.1\u0027, os.name: \u0027Windows 10\u0027, os.arch: \u0027amd64\u0027, os.version: \u002710.0\u0027, java.version: \u00271.8.0_281\u0027\nDriver info: org.openqa.selenium.chrome.ChromeDriver\nCapabilities {acceptInsecureCerts: false, browserName: chrome, browserVersion: 103.0.5060.66, chrome: {chromedriverVersion: 103.0.5060.53 (a1711811edd7..., userDataDir: C:\\Users\\Luman\\AppData\\Loca...}, goog:chromeOptions: {debuggerAddress: localhost:52653}, javascriptEnabled: true, networkConnectionEnabled: false, pageLoadStrategy: normal, platform: WINDOWS, platformName: WINDOWS, proxy: Proxy(), setWindowRect: true, strictFileInteractability: false, timeouts: {implicit: 0, pageLoad: 300000, script: 30000}, unhandledPromptBehavior: dismiss and notify, webauthn:extension:credBlob: true, webauthn:extension:largeBlob: true, webauthn:virtualAuthenticators: true}\nSession ID: 56e9a8e4f1a461a1426671a1c28a0d45\r\n\tat sun.reflect.NativeConstructorAccessorImpl.newInstance0(Native Method)\r\n\tat sun.reflect.NativeConstructorAccessorImpl.newInstance(Unknown Source)\r\n\tat sun.reflect.DelegatingConstructorAccessorImpl.newInstance(Unknown Source)\r\n\tat java.lang.reflect.Constructor.newInstance(Unknown Source)\r\n\tat org.openqa.selenium.remote.http.W3CHttpResponseCodec.createException(W3CHttpResponseCodec.java:187)\r\n\tat org.openqa.selenium.remote.http.W3CHttpResponseCodec.decode(W3CHttpResponseCodec.java:122)\r\n\tat org.openqa.selenium.remote.http.W3CHttpResponseCodec.decode(W3CHttpResponseCodec.java:49)\r\n\tat org.openqa.selenium.remote.HttpCommandExecutor.execute(HttpCommandExecutor.java:158)\r\n\tat org.openqa.selenium.remote.service.DriverCommandExecutor.execute(DriverCommandExecutor.java:83)\r\n\tat org.openqa.selenium.remote.RemoteWebDriver.execute(RemoteWebDriver.java:552)\r\n\tat org.openqa.selenium.remote.RemoteWebDriver.get(RemoteWebDriver.java:277)\r\n\tat com.Adcitin_And_Cucumber.BaseClass.getUrl(BaseClass.java:60)\r\n\tat com.stepdefination.StepDefinination.user_Must_Launch_The_Url_Of_Adacitin(StepDefinination.java:43)\r\n\tat ✽.Given user Must Launch The Url Of Adacitin(Adacitin.feature:5)\r\n",
              "status": "failed"
            },
            "line": 5,
            "name": "user Must Launch The Url Of Adacitin",
            "match": {
              "location": "StepDefinination.user_Must_Launch_The_Url_Of_Adacitin()"
            },
            "keyword": "Given "
          },
          {
            "result": {
              "status": "skipped"
            },
            "line": 6,
            "name": "user Entering The \"Palaptine\" In The Username Field",
            "match": {
              "arguments": [
                {
                  "val": "Palaptine",
                  "offset": 19
                }
              ],
              "location": "StepDefinination.user_Entering_The_In_The_Username_Field(String)"
            },
            "matchedColumns": [
              0
            ],
            "keyword": "When "
          },
          {
            "result": {
              "status": "skipped"
            },
            "line": 7,
            "name": "user Entering The \"darkowner345\" In The Password Field",
            "match": {
              "arguments": [
                {
                  "val": "darkowner345",
                  "offset": 19
                }
              ],
              "location": "StepDefinination.user_Entering_The_In_The_Password_Field(String)"
            },
            "matchedColumns": [
              1
            ],
            "keyword": "And "
          },
          {
            "result": {
              "status": "skipped"
            },
            "line": 8,
            "name": "user Click The Login Button And It Navigates To The Search Hotel Page",
            "match": {
              "location": "StepDefinination.user_Click_The_Login_Button_And_It_Navigates_To_The_Search_Hotel_Page()"
            },
            "keyword": "Then "
          }
        ],
        "tags": [
          {
            "line": 3,
            "name": "@Login"
          }
        ]
      },
      {
        "before": [
          {
            "result": {
              "duration": 135300,
              "status": "passed"
            },
            "match": {
              "location": "StepDefinination.beforeHooks(Scenario)"
            }
          }
        ],
        "line": 14,
        "name": "Login functionality",
        "description": "",
        "id": "checking-the-booking-functionality-of-adacitin-app;login-functionality;;4",
        "after": [
          {
            "result": {
              "duration": 356714700,
              "status": "passed"
            },
            "match": {
              "location": "StepDefinination.afterHooks(Scenario)"
            }
          }
        ],
        "type": "scenario",
        "keyword": "Scenario Outline",
        "steps": [
          {
            "result": {
              "duration": 508025200,
              "error_message": "org.openqa.selenium.WebDriverException: unknown error: net::ERR_INTERNET_DISCONNECTED\n  (Session info: chrome\u003d103.0.5060.66)\nBuild info: version: \u00273.141.59\u0027, revision: \u0027e82be7d358\u0027, time: \u00272018-11-14T08:17:03\u0027\nSystem info: host: \u0027DESKTOP-2V7MRDA\u0027, ip: \u0027127.0.0.1\u0027, os.name: \u0027Windows 10\u0027, os.arch: \u0027amd64\u0027, os.version: \u002710.0\u0027, java.version: \u00271.8.0_281\u0027\nDriver info: org.openqa.selenium.chrome.ChromeDriver\nCapabilities {acceptInsecureCerts: false, browserName: chrome, browserVersion: 103.0.5060.66, chrome: {chromedriverVersion: 103.0.5060.53 (a1711811edd7..., userDataDir: C:\\Users\\Luman\\AppData\\Loca...}, goog:chromeOptions: {debuggerAddress: localhost:52653}, javascriptEnabled: true, networkConnectionEnabled: false, pageLoadStrategy: normal, platform: WINDOWS, platformName: WINDOWS, proxy: Proxy(), setWindowRect: true, strictFileInteractability: false, timeouts: {implicit: 0, pageLoad: 300000, script: 30000}, unhandledPromptBehavior: dismiss and notify, webauthn:extension:credBlob: true, webauthn:extension:largeBlob: true, webauthn:virtualAuthenticators: true}\nSession ID: 56e9a8e4f1a461a1426671a1c28a0d45\r\n\tat sun.reflect.NativeConstructorAccessorImpl.newInstance0(Native Method)\r\n\tat sun.reflect.NativeConstructorAccessorImpl.newInstance(Unknown Source)\r\n\tat sun.reflect.DelegatingConstructorAccessorImpl.newInstance(Unknown Source)\r\n\tat java.lang.reflect.Constructor.newInstance(Unknown Source)\r\n\tat org.openqa.selenium.remote.http.W3CHttpResponseCodec.createException(W3CHttpResponseCodec.java:187)\r\n\tat org.openqa.selenium.remote.http.W3CHttpResponseCodec.decode(W3CHttpResponseCodec.java:122)\r\n\tat org.openqa.selenium.remote.http.W3CHttpResponseCodec.decode(W3CHttpResponseCodec.java:49)\r\n\tat org.openqa.selenium.remote.HttpCommandExecutor.execute(HttpCommandExecutor.java:158)\r\n\tat org.openqa.selenium.remote.service.DriverCommandExecutor.execute(DriverCommandExecutor.java:83)\r\n\tat org.openqa.selenium.remote.RemoteWebDriver.execute(RemoteWebDriver.java:552)\r\n\tat org.openqa.selenium.remote.RemoteWebDriver.get(RemoteWebDriver.java:277)\r\n\tat com.Adcitin_And_Cucumber.BaseClass.getUrl(BaseClass.java:60)\r\n\tat com.stepdefination.StepDefinination.user_Must_Launch_The_Url_Of_Adacitin(StepDefinination.java:43)\r\n\tat ✽.Given user Must Launch The Url Of Adacitin(Adacitin.feature:5)\r\n",
              "status": "failed"
            },
            "line": 5,
            "name": "user Must Launch The Url Of Adacitin",
            "match": {
              "location": "StepDefinination.user_Must_Launch_The_Url_Of_Adacitin()"
            },
            "keyword": "Given "
          },
          {
            "result": {
              "status": "skipped"
            },
            "line": 6,
            "name": "user Entering The \"HarryPotter\" In The Username Field",
            "match": {
              "arguments": [
                {
                  "val": "HarryPotter",
                  "offset": 19
                }
              ],
              "location": "StepDefinination.user_Entering_The_In_The_Username_Field(String)"
            },
            "matchedColumns": [
              0
            ],
            "keyword": "When "
          },
          {
            "result": {
              "status": "skipped"
            },
            "line": 7,
            "name": "user Entering The \"45cupboard\" In The Password Field",
            "match": {
              "arguments": [
                {
                  "val": "45cupboard",
                  "offset": 19
                }
              ],
              "location": "StepDefinination.user_Entering_The_In_The_Password_Field(String)"
            },
            "matchedColumns": [
              1
            ],
            "keyword": "And "
          },
          {
            "result": {
              "status": "skipped"
            },
            "line": 8,
            "name": "user Click The Login Button And It Navigates To The Search Hotel Page",
            "match": {
              "location": "StepDefinination.user_Click_The_Login_Button_And_It_Navigates_To_The_Search_Hotel_Page()"
            },
            "keyword": "Then "
          }
        ],
        "tags": [
          {
            "line": 3,
            "name": "@Login"
          }
        ]
      },
      {
        "before": [
          {
            "result": {
              "duration": 121400,
              "status": "passed"
            },
            "match": {
              "location": "StepDefinination.beforeHooks(Scenario)"
            }
          }
        ],
        "line": 15,
        "name": "Login functionality",
        "description": "",
        "id": "checking-the-booking-functionality-of-adacitin-app;login-functionality;;5",
        "after": [
          {
            "result": {
              "duration": 255890600,
              "status": "passed"
            },
            "match": {
              "location": "StepDefinination.afterHooks(Scenario)"
            }
          }
        ],
        "type": "scenario",
        "keyword": "Scenario Outline",
        "steps": [
          {
            "result": {
              "duration": 555625800,
              "error_message": "org.openqa.selenium.WebDriverException: unknown error: net::ERR_INTERNET_DISCONNECTED\n  (Session info: chrome\u003d103.0.5060.66)\nBuild info: version: \u00273.141.59\u0027, revision: \u0027e82be7d358\u0027, time: \u00272018-11-14T08:17:03\u0027\nSystem info: host: \u0027DESKTOP-2V7MRDA\u0027, ip: \u0027127.0.0.1\u0027, os.name: \u0027Windows 10\u0027, os.arch: \u0027amd64\u0027, os.version: \u002710.0\u0027, java.version: \u00271.8.0_281\u0027\nDriver info: org.openqa.selenium.chrome.ChromeDriver\nCapabilities {acceptInsecureCerts: false, browserName: chrome, browserVersion: 103.0.5060.66, chrome: {chromedriverVersion: 103.0.5060.53 (a1711811edd7..., userDataDir: C:\\Users\\Luman\\AppData\\Loca...}, goog:chromeOptions: {debuggerAddress: localhost:52653}, javascriptEnabled: true, networkConnectionEnabled: false, pageLoadStrategy: normal, platform: WINDOWS, platformName: WINDOWS, proxy: Proxy(), setWindowRect: true, strictFileInteractability: false, timeouts: {implicit: 0, pageLoad: 300000, script: 30000}, unhandledPromptBehavior: dismiss and notify, webauthn:extension:credBlob: true, webauthn:extension:largeBlob: true, webauthn:virtualAuthenticators: true}\nSession ID: 56e9a8e4f1a461a1426671a1c28a0d45\r\n\tat sun.reflect.NativeConstructorAccessorImpl.newInstance0(Native Method)\r\n\tat sun.reflect.NativeConstructorAccessorImpl.newInstance(Unknown Source)\r\n\tat sun.reflect.DelegatingConstructorAccessorImpl.newInstance(Unknown Source)\r\n\tat java.lang.reflect.Constructor.newInstance(Unknown Source)\r\n\tat org.openqa.selenium.remote.http.W3CHttpResponseCodec.createException(W3CHttpResponseCodec.java:187)\r\n\tat org.openqa.selenium.remote.http.W3CHttpResponseCodec.decode(W3CHttpResponseCodec.java:122)\r\n\tat org.openqa.selenium.remote.http.W3CHttpResponseCodec.decode(W3CHttpResponseCodec.java:49)\r\n\tat org.openqa.selenium.remote.HttpCommandExecutor.execute(HttpCommandExecutor.java:158)\r\n\tat org.openqa.selenium.remote.service.DriverCommandExecutor.execute(DriverCommandExecutor.java:83)\r\n\tat org.openqa.selenium.remote.RemoteWebDriver.execute(RemoteWebDriver.java:552)\r\n\tat org.openqa.selenium.remote.RemoteWebDriver.get(RemoteWebDriver.java:277)\r\n\tat com.Adcitin_And_Cucumber.BaseClass.getUrl(BaseClass.java:60)\r\n\tat com.stepdefination.StepDefinination.user_Must_Launch_The_Url_Of_Adacitin(StepDefinination.java:43)\r\n\tat ✽.Given user Must Launch The Url Of Adacitin(Adacitin.feature:5)\r\n",
              "status": "failed"
            },
            "line": 5,
            "name": "user Must Launch The Url Of Adacitin",
            "match": {
              "location": "StepDefinination.user_Must_Launch_The_Url_Of_Adacitin()"
            },
            "keyword": "Given "
          },
          {
            "result": {
              "status": "skipped"
            },
            "line": 6,
            "name": "user Entering The \"anivader\" In The Username Field",
            "match": {
              "arguments": [
                {
                  "val": "anivader",
                  "offset": 19
                }
              ],
              "location": "StepDefinination.user_Entering_The_In_The_Username_Field(String)"
            },
            "matchedColumns": [
              0
            ],
            "keyword": "When "
          },
          {
            "result": {
              "status": "skipped"
            },
            "line": 7,
            "name": "user Entering The \"N1l@b@nu\" In The Password Field",
            "match": {
              "arguments": [
                {
                  "val": "N1l@b@nu",
                  "offset": 19
                }
              ],
              "location": "StepDefinination.user_Entering_The_In_The_Password_Field(String)"
            },
            "matchedColumns": [
              1
            ],
            "keyword": "And "
          },
          {
            "result": {
              "status": "skipped"
            },
            "line": 8,
            "name": "user Click The Login Button And It Navigates To The Search Hotel Page",
            "match": {
              "location": "StepDefinination.user_Click_The_Login_Button_And_It_Navigates_To_The_Search_Hotel_Page()"
            },
            "keyword": "Then "
          }
        ],
        "tags": [
          {
            "line": 3,
            "name": "@Login"
          }
        ]
      },
      {
        "before": [
          {
            "result": {
              "duration": 155700,
              "status": "passed"
            },
            "match": {
              "location": "StepDefinination.beforeHooks(Scenario)"
            }
          }
        ],
        "line": 17,
        "name": "Hotel Search functionality",
        "description": "",
        "id": "checking-the-booking-functionality-of-adacitin-app;hotel-search-functionality",
        "after": [
          {
            "result": {
              "duration": 203907300,
              "status": "passed"
            },
            "match": {
              "location": "StepDefinination.afterHooks(Scenario)"
            }
          }
        ],
        "type": "scenario",
        "keyword": "Scenario",
        "steps": [
          {
            "result": {
              "duration": 314003800,
              "error_message": "org.openqa.selenium.NoSuchElementException: no such element: Unable to locate element: {\"method\":\"xpath\",\"selector\":\"//*[@id\u003d\"location\"]\"}\n  (Session info: chrome\u003d103.0.5060.66)\nFor documentation on this error, please visit: https://www.seleniumhq.org/exceptions/no_such_element.html\nBuild info: version: \u00273.141.59\u0027, revision: \u0027e82be7d358\u0027, time: \u00272018-11-14T08:17:03\u0027\nSystem info: host: \u0027DESKTOP-2V7MRDA\u0027, ip: \u0027127.0.0.1\u0027, os.name: \u0027Windows 10\u0027, os.arch: \u0027amd64\u0027, os.version: \u002710.0\u0027, java.version: \u00271.8.0_281\u0027\nDriver info: org.openqa.selenium.chrome.ChromeDriver\nCapabilities {acceptInsecureCerts: false, browserName: chrome, browserVersion: 103.0.5060.66, chrome: {chromedriverVersion: 103.0.5060.53 (a1711811edd7..., userDataDir: C:\\Users\\Luman\\AppData\\Loca...}, goog:chromeOptions: {debuggerAddress: localhost:52653}, javascriptEnabled: true, networkConnectionEnabled: false, pageLoadStrategy: normal, platform: WINDOWS, platformName: WINDOWS, proxy: Proxy(), setWindowRect: true, strictFileInteractability: false, timeouts: {implicit: 0, pageLoad: 300000, script: 30000}, unhandledPromptBehavior: dismiss and notify, webauthn:extension:credBlob: true, webauthn:extension:largeBlob: true, webauthn:virtualAuthenticators: true}\nSession ID: 56e9a8e4f1a461a1426671a1c28a0d45\n*** Element info: {Using\u003dxpath, value\u003d//*[@id\u003d\"location\"]}\r\n\tat sun.reflect.NativeConstructorAccessorImpl.newInstance0(Native Method)\r\n\tat sun.reflect.NativeConstructorAccessorImpl.newInstance(Unknown Source)\r\n\tat sun.reflect.DelegatingConstructorAccessorImpl.newInstance(Unknown Source)\r\n\tat java.lang.reflect.Constructor.newInstance(Unknown Source)\r\n\tat org.openqa.selenium.remote.http.W3CHttpResponseCodec.createException(W3CHttpResponseCodec.java:187)\r\n\tat org.openqa.selenium.remote.http.W3CHttpResponseCodec.decode(W3CHttpResponseCodec.java:122)\r\n\tat org.openqa.selenium.remote.http.W3CHttpResponseCodec.decode(W3CHttpResponseCodec.java:49)\r\n\tat org.openqa.selenium.remote.HttpCommandExecutor.execute(HttpCommandExecutor.java:158)\r\n\tat org.openqa.selenium.remote.service.DriverCommandExecutor.execute(DriverCommandExecutor.java:83)\r\n\tat org.openqa.selenium.remote.RemoteWebDriver.execute(RemoteWebDriver.java:552)\r\n\tat org.openqa.selenium.remote.RemoteWebDriver.findElement(RemoteWebDriver.java:323)\r\n\tat org.openqa.selenium.remote.RemoteWebDriver.findElementByXPath(RemoteWebDriver.java:428)\r\n\tat org.openqa.selenium.By$ByXPath.findElement(By.java:353)\r\n\tat org.openqa.selenium.remote.RemoteWebDriver.findElement(RemoteWebDriver.java:315)\r\n\tat org.openqa.selenium.support.pagefactory.DefaultElementLocator.findElement(DefaultElementLocator.java:69)\r\n\tat org.openqa.selenium.support.pagefactory.internal.LocatingElementHandler.invoke(LocatingElementHandler.java:38)\r\n\tat com.sun.proxy.$Proxy19.getTagName(Unknown Source)\r\n\tat org.openqa.selenium.support.ui.Select.\u003cinit\u003e(Select.java:45)\r\n\tat com.Adcitin_And_Cucumber.BaseClass.hotelBooking(BaseClass.java:91)\r\n\tat com.stepdefination.StepDefinination.user_Selecting_The_From_HotelLocation_DropDown(StepDefinination.java:71)\r\n\tat ✽.When user Selecting The \"London\" From HotelLocation DropDown(Adacitin.feature:18)\r\n",
              "status": "failed"
            },
            "line": 18,
            "name": "user Selecting The \"London\" From HotelLocation DropDown",
            "match": {
              "arguments": [
                {
                  "val": "London",
                  "offset": 20
                }
              ],
              "location": "StepDefinination.user_Selecting_The_From_HotelLocation_DropDown(String)"
            },
            "keyword": "When "
          },
          {
            "result": {
              "status": "skipped"
            },
            "line": 19,
            "name": "user Selecting The \"Hotel Creek\" From HotelSelection DropDown",
            "match": {
              "arguments": [
                {
                  "val": "Hotel Creek",
                  "offset": 20
                }
              ],
              "location": "StepDefinination.user_Selecting_The_From_HotelSelection_DropDown(String)"
            },
            "keyword": "And "
          },
          {
            "result": {
              "status": "skipped"
            },
            "line": 20,
            "name": "user Selecting The \"Super Deluxe\" From RoomType DropDown",
            "match": {
              "arguments": [
                {
                  "val": "Super Deluxe",
                  "offset": 20
                }
              ],
              "location": "StepDefinination.user_Selecting_The_From_RoomType_DropDown(String)"
            },
            "keyword": "And "
          },
          {
            "result": {
              "status": "skipped"
            },
            "line": 21,
            "name": "user Selecting The \"10\" From Numbers Of Room  DropDown",
            "match": {
              "arguments": [
                {
                  "val": "10",
                  "offset": 20
                }
              ],
              "location": "StepDefinination.user_Selecting_The_From_Numbers_Of_Room_DropDown(String)"
            },
            "keyword": "And "
          },
          {
            "result": {
              "status": "skipped"
            },
            "line": 22,
            "name": "user Selecting The \"4\" From Adult Per Room DropDown",
            "match": {
              "arguments": [
                {
                  "val": "4",
                  "offset": 20
                }
              ],
              "location": "StepDefinination.user_Selecting_The_From_Adult_Per_Room_DropDown(String)"
            },
            "keyword": "And "
          },
          {
            "result": {
              "status": "skipped"
            },
            "line": 23,
            "name": "user Selecting The \"4\" From Child Per Room DropDown",
            "match": {
              "arguments": [
                {
                  "val": "4",
                  "offset": 20
                }
              ],
              "location": "StepDefinination.user_Selecting_The_From_Child_Per_Room_DropDown(String)"
            },
            "keyword": "And "
          },
          {
            "result": {
              "status": "skipped"
            },
            "line": 24,
            "name": "user Click The search Button And It Navigates To The Select Hotel Page",
            "match": {
              "location": "StepDefinination.user_Click_The_search_Button_And_It_Navigates_To_The_Select_Hotel_Page()"
            },
            "keyword": "Then "
          }
        ]
      },
      {
        "before": [
          {
            "result": {
              "duration": 98500,
              "status": "passed"
            },
            "match": {
              "location": "StepDefinination.beforeHooks(Scenario)"
            }
          }
        ],
        "line": 26,
        "name": "Radio Button Functionality",
        "description": "",
        "id": "checking-the-booking-functionality-of-adacitin-app;radio-button-functionality",
        "after": [
          {
            "result": {
              "duration": 286411500,
              "status": "passed"
            },
            "match": {
              "location": "StepDefinination.afterHooks(Scenario)"
            }
          }
        ],
        "type": "scenario",
        "keyword": "Scenario",
        "steps": [
          {
            "result": {
              "duration": 45064300,
              "error_message": "org.openqa.selenium.NoSuchElementException: no such element: Unable to locate element: {\"method\":\"xpath\",\"selector\":\"//*[@id\u003d\"radiobutton_0\"]\"}\n  (Session info: chrome\u003d103.0.5060.66)\nFor documentation on this error, please visit: https://www.seleniumhq.org/exceptions/no_such_element.html\nBuild info: version: \u00273.141.59\u0027, revision: \u0027e82be7d358\u0027, time: \u00272018-11-14T08:17:03\u0027\nSystem info: host: \u0027DESKTOP-2V7MRDA\u0027, ip: \u0027127.0.0.1\u0027, os.name: \u0027Windows 10\u0027, os.arch: \u0027amd64\u0027, os.version: \u002710.0\u0027, java.version: \u00271.8.0_281\u0027\nDriver info: org.openqa.selenium.chrome.ChromeDriver\nCapabilities {acceptInsecureCerts: false, browserName: chrome, browserVersion: 103.0.5060.66, chrome: {chromedriverVersion: 103.0.5060.53 (a1711811edd7..., userDataDir: C:\\Users\\Luman\\AppData\\Loca...}, goog:chromeOptions: {debuggerAddress: localhost:52653}, javascriptEnabled: true, networkConnectionEnabled: false, pageLoadStrategy: normal, platform: WINDOWS, platformName: WINDOWS, proxy: Proxy(), setWindowRect: true, strictFileInteractability: false, timeouts: {implicit: 0, pageLoad: 300000, script: 30000}, unhandledPromptBehavior: dismiss and notify, webauthn:extension:credBlob: true, webauthn:extension:largeBlob: true, webauthn:virtualAuthenticators: true}\nSession ID: 56e9a8e4f1a461a1426671a1c28a0d45\n*** Element info: {Using\u003dxpath, value\u003d//*[@id\u003d\"radiobutton_0\"]}\r\n\tat sun.reflect.NativeConstructorAccessorImpl.newInstance0(Native Method)\r\n\tat sun.reflect.NativeConstructorAccessorImpl.newInstance(Unknown Source)\r\n\tat sun.reflect.DelegatingConstructorAccessorImpl.newInstance(Unknown Source)\r\n\tat java.lang.reflect.Constructor.newInstance(Unknown Source)\r\n\tat org.openqa.selenium.remote.http.W3CHttpResponseCodec.createException(W3CHttpResponseCodec.java:187)\r\n\tat org.openqa.selenium.remote.http.W3CHttpResponseCodec.decode(W3CHttpResponseCodec.java:122)\r\n\tat org.openqa.selenium.remote.http.W3CHttpResponseCodec.decode(W3CHttpResponseCodec.java:49)\r\n\tat org.openqa.selenium.remote.HttpCommandExecutor.execute(HttpCommandExecutor.java:158)\r\n\tat org.openqa.selenium.remote.service.DriverCommandExecutor.execute(DriverCommandExecutor.java:83)\r\n\tat org.openqa.selenium.remote.RemoteWebDriver.execute(RemoteWebDriver.java:552)\r\n\tat org.openqa.selenium.remote.RemoteWebDriver.findElement(RemoteWebDriver.java:323)\r\n\tat org.openqa.selenium.remote.RemoteWebDriver.findElementByXPath(RemoteWebDriver.java:428)\r\n\tat org.openqa.selenium.By$ByXPath.findElement(By.java:353)\r\n\tat org.openqa.selenium.remote.RemoteWebDriver.findElement(RemoteWebDriver.java:315)\r\n\tat org.openqa.selenium.support.pagefactory.DefaultElementLocator.findElement(DefaultElementLocator.java:69)\r\n\tat org.openqa.selenium.support.pagefactory.internal.LocatingElementHandler.invoke(LocatingElementHandler.java:38)\r\n\tat com.sun.proxy.$Proxy19.click(Unknown Source)\r\n\tat com.Adcitin_And_Cucumber.BaseClass.radiobutton(BaseClass.java:99)\r\n\tat com.stepdefination.StepDefinination.user_Selecting_The_Radio_Button(StepDefinination.java:114)\r\n\tat ✽.When user Selecting The Radio Button(Adacitin.feature:27)\r\n",
              "status": "failed"
            },
            "line": 27,
            "name": "user Selecting The Radio Button",
            "match": {
              "location": "StepDefinination.user_Selecting_The_Radio_Button()"
            },
            "keyword": "When "
          },
          {
            "result": {
              "status": "skipped"
            },
            "line": 28,
            "name": "user Selecting The Continue And It Navigates To The Book A Hotel Page",
            "match": {
              "location": "StepDefinination.user_Selecting_The_Continue_And_It_Navigates_To_The_Book_A_Hotel_Page()"
            },
            "keyword": "Then "
          }
        ]
      },
      {
        "before": [
          {
            "result": {
              "duration": 2673100,
              "status": "passed"
            },
            "match": {
              "location": "StepDefinination.beforeHooks(Scenario)"
            }
          }
        ],
        "line": 30,
        "name": "Hotel Book functionality",
        "description": "",
        "id": "checking-the-booking-functionality-of-adacitin-app;hotel-book-functionality",
        "after": [
          {
            "result": {
              "duration": 252696900,
              "status": "passed"
            },
            "match": {
              "location": "StepDefinination.afterHooks(Scenario)"
            }
          }
        ],
        "type": "scenario",
        "keyword": "Scenario",
        "steps": [
          {
            "result": {
              "duration": 65291500,
              "error_message": "org.openqa.selenium.NoSuchElementException: no such element: Unable to locate element: {\"method\":\"xpath\",\"selector\":\"//*[@id\u003d\"first_name\"]\"}\n  (Session info: chrome\u003d103.0.5060.66)\nFor documentation on this error, please visit: https://www.seleniumhq.org/exceptions/no_such_element.html\nBuild info: version: \u00273.141.59\u0027, revision: \u0027e82be7d358\u0027, time: \u00272018-11-14T08:17:03\u0027\nSystem info: host: \u0027DESKTOP-2V7MRDA\u0027, ip: \u0027127.0.0.1\u0027, os.name: \u0027Windows 10\u0027, os.arch: \u0027amd64\u0027, os.version: \u002710.0\u0027, java.version: \u00271.8.0_281\u0027\nDriver info: org.openqa.selenium.chrome.ChromeDriver\nCapabilities {acceptInsecureCerts: false, browserName: chrome, browserVersion: 103.0.5060.66, chrome: {chromedriverVersion: 103.0.5060.53 (a1711811edd7..., userDataDir: C:\\Users\\Luman\\AppData\\Loca...}, goog:chromeOptions: {debuggerAddress: localhost:52653}, javascriptEnabled: true, networkConnectionEnabled: false, pageLoadStrategy: normal, platform: WINDOWS, platformName: WINDOWS, proxy: Proxy(), setWindowRect: true, strictFileInteractability: false, timeouts: {implicit: 0, pageLoad: 300000, script: 30000}, unhandledPromptBehavior: dismiss and notify, webauthn:extension:credBlob: true, webauthn:extension:largeBlob: true, webauthn:virtualAuthenticators: true}\nSession ID: 56e9a8e4f1a461a1426671a1c28a0d45\n*** Element info: {Using\u003dxpath, value\u003d//*[@id\u003d\"first_name\"]}\r\n\tat sun.reflect.NativeConstructorAccessorImpl.newInstance0(Native Method)\r\n\tat sun.reflect.NativeConstructorAccessorImpl.newInstance(Unknown Source)\r\n\tat sun.reflect.DelegatingConstructorAccessorImpl.newInstance(Unknown Source)\r\n\tat java.lang.reflect.Constructor.newInstance(Unknown Source)\r\n\tat org.openqa.selenium.remote.http.W3CHttpResponseCodec.createException(W3CHttpResponseCodec.java:187)\r\n\tat org.openqa.selenium.remote.http.W3CHttpResponseCodec.decode(W3CHttpResponseCodec.java:122)\r\n\tat org.openqa.selenium.remote.http.W3CHttpResponseCodec.decode(W3CHttpResponseCodec.java:49)\r\n\tat org.openqa.selenium.remote.HttpCommandExecutor.execute(HttpCommandExecutor.java:158)\r\n\tat org.openqa.selenium.remote.service.DriverCommandExecutor.execute(DriverCommandExecutor.java:83)\r\n\tat org.openqa.selenium.remote.RemoteWebDriver.execute(RemoteWebDriver.java:552)\r\n\tat org.openqa.selenium.remote.RemoteWebDriver.findElement(RemoteWebDriver.java:323)\r\n\tat org.openqa.selenium.remote.RemoteWebDriver.findElementByXPath(RemoteWebDriver.java:428)\r\n\tat org.openqa.selenium.By$ByXPath.findElement(By.java:353)\r\n\tat org.openqa.selenium.remote.RemoteWebDriver.findElement(RemoteWebDriver.java:315)\r\n\tat org.openqa.selenium.support.pagefactory.DefaultElementLocator.findElement(DefaultElementLocator.java:69)\r\n\tat org.openqa.selenium.support.pagefactory.internal.LocatingElementHandler.invoke(LocatingElementHandler.java:38)\r\n\tat com.sun.proxy.$Proxy19.sendKeys(Unknown Source)\r\n\tat com.Adcitin_And_Cucumber.BaseClass.passInput(BaseClass.java:78)\r\n\tat com.stepdefination.StepDefinination.user_Entering_The_In_The_Firstname_Field(StepDefinination.java:127)\r\n\tat ✽.When user Entering The \"Safwan Ali\" In The Firstname Field(Adacitin.feature:31)\r\n",
              "status": "failed"
            },
            "line": 31,
            "name": "user Entering The \"Safwan Ali\" In The Firstname Field",
            "match": {
              "arguments": [
                {
                  "val": "Safwan Ali",
                  "offset": 19
                }
              ],
              "location": "StepDefinination.user_Entering_The_In_The_Firstname_Field(String)"
            },
            "keyword": "When "
          },
          {
            "result": {
              "status": "skipped"
            },
            "line": 32,
            "name": "user Entering The \"Tajudeen\" In The Lastname Field",
            "match": {
              "arguments": [
                {
                  "val": "Tajudeen",
                  "offset": 19
                }
              ],
              "location": "StepDefinination.user_Entering_The_In_The_Lastname_Field(String)"
            },
            "keyword": "And "
          },
          {
            "result": {
              "status": "skipped"
            },
            "line": 33,
            "name": "user Entering The \"Mr. H.potter, the cupboard under the stairs,4,Private drive,Little Whinging, SURREY,LONDON\" In The Billing Address Field",
            "match": {
              "arguments": [
                {
                  "val": "Mr. H.potter, the cupboard under the stairs,4,Private drive,Little Whinging, SURREY,LONDON",
                  "offset": 19
                }
              ],
              "location": "StepDefinination.user_Entering_The_In_The_Billing_Address_Field(String)"
            },
            "keyword": "And "
          },
          {
            "result": {
              "status": "skipped"
            },
            "line": 34,
            "name": "user Entering The \"1234567898765432\" In The Cardnumber Field",
            "match": {
              "arguments": [
                {
                  "val": "1234567898765432",
                  "offset": 19
                }
              ],
              "location": "StepDefinination.user_Entering_The_In_The_Cardnumber_Field(String)"
            },
            "keyword": "And "
          },
          {
            "result": {
              "status": "skipped"
            },
            "line": 35,
            "name": "user Selecting The \"VISA\" From Cardtype DropDown",
            "match": {
              "arguments": [
                {
                  "val": "VISA",
                  "offset": 20
                }
              ],
              "location": "StepDefinination.user_Selecting_The_From_Cardtype_DropDown(String)"
            },
            "keyword": "And "
          },
          {
            "result": {
              "status": "skipped"
            },
            "line": 36,
            "name": "user Selecting The \"12\" From ExpiryMonth DropDown",
            "match": {
              "arguments": [
                {
                  "val": "12",
                  "offset": 20
                }
              ],
              "location": "StepDefinination.user_Selecting_The_From_ExpiryMonth_DropDown(String)"
            },
            "keyword": "And "
          },
          {
            "result": {
              "status": "skipped"
            },
            "line": 37,
            "name": "user Selecting The \"2022\" From ExpiryYear DropDown",
            "match": {
              "arguments": [
                {
                  "val": "2022",
                  "offset": 20
                }
              ],
              "location": "StepDefinination.user_Selecting_The_From_ExpiryYear_DropDown(String)"
            },
            "keyword": "And "
          },
          {
            "result": {
              "status": "skipped"
            },
            "line": 38,
            "name": "user Entering The \"365\" In The CVVnumber Field",
            "match": {
              "arguments": [
                {
                  "val": "365",
                  "offset": 19
                }
              ],
              "location": "StepDefinination.user_Entering_The_In_The_CVVnumber_Field(String)"
            },
            "keyword": "And "
          },
          {
            "result": {
              "status": "skipped"
            },
            "line": 39,
            "name": "user Click The Booknow Button And It Navigates To The Select Hotel Page",
            "match": {
              "location": "StepDefinination.user_Click_The_Booknow_Button_And_It_Navigates_To_The_Select_Hotel_Page()"
            },
            "keyword": "Then "
          }
        ]
      },
      {
        "before": [
          {
            "result": {
              "duration": 105300,
              "status": "passed"
            },
            "match": {
              "location": "StepDefinination.beforeHooks(Scenario)"
            }
          }
        ],
        "line": 47,
        "name": "ScreenShot functionality",
        "description": "",
        "id": "checking-the-booking-functionality-of-adacitin-app;screenshot-functionality",
        "after": [
          {
            "result": {
              "duration": 89000,
              "status": "passed"
            },
            "match": {
              "location": "StepDefinination.afterHooks(Scenario)"
            }
          }
        ],
        "type": "scenario",
        "keyword": "Scenario",
        "steps": [
          {
            "result": {
              "duration": 274185300,
              "status": "passed"
            },
            "line": 48,
            "name": "user TkesScreenshot",
            "match": {
              "location": "StepDefinination.user_TkesScreenshot()"
            },
            "keyword": "And "
          }
        ]
      }
    ],
    "name": "checking the booking functionality of Adacitin app",
    "description": "",
    "id": "checking-the-booking-functionality-of-adacitin-app",
    "keyword": "Feature",
    "uri": "Adacitin.feature"
  }
]